{
    "categories" : [
        { 
        "name" : "grocery",
        "limit" : 100.50,
        "listOfExpense" : [
               50.00,
               20.90

            ],
            "dates" : [
                "2024-06-10",
                "2024-01-01"

            ]
        },
        {
        "name" : "bills",
        "limit" : 330.00,
        "listOfExpense" : [
            60.80,
            30.70

            ],
            "dates" : [
                "2023-01-02",
                "2024-01-03"

            ]
        }
    ],
    
    "totalBudget" : 430.50
}